<?xml version="1.0" encoding="UTF-8"?>
<window id="104">
    <defaultcontrol>1</defaultcontrol>
    <animation type="WindowOpen" reversible="false">
        <effect type="zoom" time="350" center="640,360" start="130" end="100" tween="sine" easing="out"/>
        <effect type="fade" time="350" start="0" tween="sine" easing="out" end="100"/>
    </animation>
    <animation type="WindowClose" reversible="false">
        <effect type="zoom" time="350" center="640,360" start="100" end="130" tween="sine" easing="in"/>
        <effect type="fade" time="350" start="100" tween="sine" easing="in" end="0"/>
    </animation>
    <animation type="Visible" reversible="false">
        <effect type="fade" time="350" start="0" tween="sine" easing="out" end="100"/>
    </animation>
    <animation type="Hidden" reversible="false">
        <effect type="fade" time="350" start="100" tween="sine" easing="in" end="0"/>
    </animation>
    <controls>
        <control type="group">
            <control type="image">
                <posx>0</posx>
                <posy>0</posy>
                <width>1280</width>
                <height>720</height>
                <texture>AURORA TINTED.jpg</texture>
            </control>
            <control type="multiimage">
                <randomize>false</randomize>
                <timeperimage>12000</timeperimage>
                <fadetime>4000</fadetime>
                <pauseatend>0</pauseatend>
                <loop>true</loop>
                <posx>0</posx>
                <posy>0</posy>
                <width>1280</width>
                <height>720</height>
                <imagepath background="true">Aurora Effect/Backgrounds</imagepath>
                <animation effect="fade" start="10" end="70" time="250" delay="0" tween="sine" easing="out">WindowOpen</animation>
                <animation effect="fade" start="70" end="0" time="250" delay="20" tween="sine" easing="out">WindowClose</animation>
            </control>
            <control type="image">
                <height>720</height>
                <width>3280</width>
                <texture>colors_pulse.png</texture>
            </control>
            <control type="image">
                <texture>spectrum0.png</texture>
            </control>
            <control type="multiimage">
                <randomize>false</randomize>
                <timeperimage>12000</timeperimage>
                <fadetime>4000</fadetime>
                <pauseatend>0</pauseatend>
                <loop>true</loop>
                <posx>766</posx>
                <posy>182</posy>
                <width>346</width>
                <height>346</height>
                <imagepath background="true">Aurora Effect/Thumbs</imagepath>
                <animation effect="fade" start="0" end="70" time="250" delay="0" tween="sine" easing="out">WindowOpen</animation>
                <animation effect="fade" start="70" end="0" time="250" delay="20" tween="sine" easing="out">WindowClose</animation>
            </control>
            <control type="image" id="1">
                <posx>758</posx>
                <posy>176</posy>
                <width>361</width>
                <height>359</height>
                <aspectratio align="center" aligny="center">stretch</aspectratio>
                <texture>thumb_back.png</texture>
            </control>
            <control type="image">
                <posx>770</posx>
                <posy>187</posy>
                <width>312</width>
                <height>313</height>
                <aspectratio align="center" aligny="center">stretch</aspectratio>
                <texture>thumbs/music_overlay.png</texture>
                <fadetime>800</fadetime>
            </control>
            <control type="image">
                <top>170</top>
                <left>640</left>
                <height>366</height>
                <width>602</width>
                <texture>views/gallery/side_shadows.png</texture>
            </control>
            <control type="image">
                <top>53</top>
                <left>762</left>
                <height>601</height>
                <width>340</width>
                <texture>views/gallery/top_bottom_shadows.png</texture>
            </control>
            <control type="image">
                <top>-58</top>
                <left>-200</left>
                <height>206</height>
                <width>1680</width>
                <texture>views/gallery/top_bottom_shadows.png</texture>
            </control>
            <control type="image">
                <top>570</top>
                <left>-200</left>
                <height>206</height>
                <width>1680</width>
                <texture>views/gallery/top_bottom_shadows.png</texture>
            </control>
            <control type="image">
                <posx>31</posx>
                <posy>307</posy>
                <width>695</width>
                <height>2</height>
                <texture>pstvButtonFocus.png</texture>
                <colordiffuse/>
            </control>
            <control type="image">
                <top>-58</top>
                <left>50</left>
                <height>206</height>
                <width>1480</width>
                <texture>views/gallery/top_bottom_shadows.png</texture>
            </control>
            <control type="image">
                <top>571</top>
                <left>50</left>
                <height>206</height>
                <width>1480</width>
                <texture>views/gallery/top_bottom_shadows.png</texture>
            </control>
            <control type="image">
                <left>-200</left>
                <top>-12</top>
                <height>737</height>
                <width>1680</width>
                <texture>views/gallery/top_bottom_shadows.png</texture>
            </control>
            <control type="image">
                <top>-58</top>
                <left>-200</left>
                <height>206</height>
                <width>1680</width>
                <texture>views/gallery/top_bottom_shadows.png</texture>
            </control>
            <control type="image">
                <top>570</top>
                <left>-200</left>
                <height>206</height>
                <width>1680</width>
                <texture>views/gallery/top_bottom_shadows.png</texture>
            </control>
            <control type="group">
                <left>1042r</left>
                <top>265</top>
                <visible>!player.passthrough</visible>
                <control type="label">
                    <description>Volume Label</description>
                    <left>2</left>
                    <top>-30</top>
                    <width>1230</width>
                    <height>29</height>
                    <label>$LOCALIZE[13376]</label>
                    <font>FontSize_120</font>
                    <textcolor>99white</textcolor>
                    <shadowcolor>99000000</shadowcolor>
                    <align>left</align>
                    <aligny>center</aligny>
                </control>
                <control type="label">
                    <description/>
                    <right>431r</right>
                    <top>130</top>
                    <width>1230</width>
                    <height>29</height>
                    <label>$INFO[Player.Volume]</label>
                    <font>FontSize_230</font>
                    <textcolor>white</textcolor>
                    <shadowcolor>99000000</shadowcolor>
                    <align>right</align>
                    <aligny>center</aligny>
                    <visible>!substring(Player.Volume,-60.0)</visible>
                </control>
                <control type="label">
                    <description>Mute Label</description>
                    <right>385r</right>
                    <top>135</top>
                    <width>1230</width>
                    <height>29</height>
                    <label>$LOCALIZE[31300]</label>
                    <font>FontSize_230</font>
                    <textcolor>white</textcolor>
                    <shadowcolor>99000000</shadowcolor>
                    <align>right</align>
                    <aligny>center</aligny>
                    <visible>substring(Player.Volume,-60.0)</visible>
                </control>
                <control type="image">
                    <left>0</left>
                    <width>191</width>
                    <height>15</height>
                    <texture>osd/volume/volume_bg.png</texture>
                </control>
            </control>
            <control type="group">
                <left>242r</left>
                <top>65</top>
                <visible>player.passthrough</visible>
                <control type="label">
                    <description>Volume Label</description>
                    <left>-3</left>
                    <top>-30</top>
                    <width>200</width>
                    <height>29</height>
                    <label>$LOCALIZE[29802]</label>
                    <font>FontSize_18</font>
                    <textcolor>99white</textcolor>
                    <shadowcolor>99000000</shadowcolor>
                    <align>left</align>
                    <aligny>center</aligny>
                </control>
                <control type="image">
                    <left>-3</left>
                    <width>198</width>
                    <height>15</height>
                    <texture>osd/volume/volume_bg.png</texture>
                </control>
            </control>
        </control>
    </controls>
</window>
